[
  {"Institution_Name":"Tel Aviv University","Country":"Israel","Region_State_Province":"Tel Aviv District","City":"Tel Aviv","Institution_Type":"Public","Website_URL":"https://www.tau.ac.il","Year_Established":1956,"Total_Student_Population":30000,"International_Student_Percentage":15,"Acceptance_Rate_Percentage":40,"Annual_Tuition_Fees_USD":10000,"QS_World_Ranking":219,"Key_Programs_Specializations":"Sciences, Engineering, Medicine, Law","Research_Output_Level":"High"},
  {"Institution_Name":"Hebrew University of Jerusalem","Country":"Israel","Region_State_Province":"Jerusalem District","City":"Jerusalem","Institution_Type":"Public","Website_URL":"https://new.huji.ac.il","Year_Established":1918,"Total_Student_Population":23000,"International_Student_Percentage":12,"Acceptance_Rate_Percentage":45,"Annual_Tuition_Fees_USD":9000,"QS_World_Ranking":165,"Key_Programs_Specializations":"Sciences, Humanities, Medicine, Law","Research_Output_Level":"High"},
  {"Institution_Name":"Technion - Israel Institute of Technology","Country":"Israel","Region_State_Province":"Haifa District","City":"Haifa","Institution_Type":"Public","Website_URL":"https://www.technion.ac.il","Year_Established":1912,"Total_Student_Population":14500,"International_Student_Percentage":12,"Acceptance_Rate_Percentage":30,"Annual_Tuition_Fees_USD":11000,"QS_World_Ranking":74,"Key_Programs_Specializations":"Engineering, Sciences, Architecture, Medicine","Research_Output_Level":"High"},
  {"Institution_Name":"King Abdullah University of Science and Technology","Country":"Saudi Arabia","Region_State_Province":"Makkah Region","City":"Thuwal","Institution_Type":"Private","Website_URL":"https://www.kaust.edu.sa","Year_Established":2009,"Total_Student_Population":2000,"International_Student_Percentage":80,"Acceptance_Rate_Percentage":10,"Annual_Tuition_Fees_USD":0,"QS_World_Ranking":101,"Key_Programs_Specializations":"Engineering, Sciences, Environmental Studies","Research_Output_Level":"High"},
  {"Institution_Name":"King Saud University","Country":"Saudi Arabia","Region_State_Province":"Riyadh Province","City":"Riyadh","Institution_Type":"Public","Website_URL":"https://www.ksu.edu.sa","Year_Established":1957,"Total_Student_Population":70000,"International_Student_Percentage":8,"Acceptance_Rate_Percentage":45,"Annual_Tuition_Fees_USD":0,"QS_World_Ranking":203,"Key_Programs_Specializations":"Medicine, Engineering, Sciences, Business","Research_Output_Level":"High"},
  {"Institution_Name":"United Arab Emirates University","Country":"United Arab Emirates","Region_State_Province":"Abu Dhabi","City":"Al Ain","Institution_Type":"Public","Website_URL":"https://www.uaeu.ac.ae","Year_Established":1976,"Total_Student_Population":14000,"International_Student_Percentage":30,"Acceptance_Rate_Percentage":55,"Annual_Tuition_Fees_USD":15000,"QS_World_Ranking":290,"Key_Programs_Specializations":"Engineering, Sciences, Medicine, Business","Research_Output_Level":"High"},
  {"Institution_Name":"Khalifa University","Country":"United Arab Emirates","Region_State_Province":"Abu Dhabi","City":"Abu Dhabi","Institution_Type":"Public","Website_URL":"https://www.ku.ac.ae","Year_Established":2007,"Total_Student_Population":5000,"International_Student_Percentage":40,"Acceptance_Rate_Percentage":40,"Annual_Tuition_Fees_USD":30000,"QS_World_Ranking":230,"Key_Programs_Specializations":"Engineering, Sciences, Medicine, Nuclear Engineering","Research_Output_Level":"High"},
  {"Institution_Name":"American University of Sharjah","Country":"United Arab Emirates","Region_State_Province":"Sharjah","City":"Sharjah","Institution_Type":"Private","Website_URL":"https://www.aus.edu","Year_Established":1997,"Total_Student_Population":6000,"International_Student_Percentage":45,"Acceptance_Rate_Percentage":50,"Annual_Tuition_Fees_USD":22000,"QS_World_Ranking":350,"Key_Programs_Specializations":"Engineering, Business, Architecture, Arts","Research_Output_Level":"Medium"},
  {"Institution_Name":"Qatar University","Country":"Qatar","Region_State_Province":"Doha","City":"Doha","Institution_Type":"Public","Website_URL":"https://www.qu.edu.qa","Year_Established":1973,"Total_Student_Population":18000,"International_Student_Percentage":25,"Acceptance_Rate_Percentage":50,"Annual_Tuition_Fees_USD":0,"QS_World_Ranking":224,"Key_Programs_Specializations":"Engineering, Sciences, Business, Arts","Research_Output_Level":"High"},
  {"Institution_Name":"Boğaziçi University","Country":"Turkey","Region_State_Province":"Istanbul","City":"Istanbul","Institution_Type":"Public","Website_URL":"https://www.boun.edu.tr","Year_Established":1863,"Total_Student_Population":16000,"International_Student_Percentage":8,"Acceptance_Rate_Percentage":5,"Annual_Tuition_Fees_USD":500,"QS_World_Ranking":454,"Key_Programs_Specializations":"Engineering, Sciences, Economics, Humanities","Research_Output_Level":"High"},
  {"Institution_Name":"Middle East Technical University","Country":"Turkey","Region_State_Province":"Ankara","City":"Ankara","Institution_Type":"Public","Website_URL":"https://www.metu.edu.tr","Year_Established":1956,"Total_Student_Population":29000,"International_Student_Percentage":10,"Acceptance_Rate_Percentage":10,"Annual_Tuition_Fees_USD":500,"QS_World_Ranking":336,"Key_Programs_Specializations":"Engineering, Architecture, Sciences, Economics","Research_Output_Level":"High"},
  {"Institution_Name":"University of Cape Town","Country":"South Africa","Region_State_Province":"Western Cape","City":"Cape Town","Institution_Type":"Public","Website_URL":"https://www.uct.ac.za","Year_Established":1829,"Total_Student_Population":29000,"International_Student_Percentage":18,"Acceptance_Rate_Percentage":40,"Annual_Tuition_Fees_USD":5000,"QS_World_Ranking":171,"Key_Programs_Specializations":"Medicine, Law, Sciences, Engineering","Research_Output_Level":"High"},
  {"Institution_Name":"University of the Witwatersrand","Country":"South Africa","Region_State_Province":"Gauteng","City":"Johannesburg","Institution_Type":"Public","Website_URL":"https://www.wits.ac.za","Year_Established":1896,"Total_Student_Population":38000,"International_Student_Percentage":12,"Acceptance_Rate_Percentage":45,"Annual_Tuition_Fees_USD":4000,"QS_World_Ranking":428,"Key_Programs_Specializations":"Medicine, Engineering, Sciences, Law","Research_Output_Level":"High"},
  {"Institution_Name":"Stellenbosch University","Country":"South Africa","Region_State_Province":"Western Cape","City":"Stellenbosch","Institution_Type":"Public","Website_URL":"https://www.sun.ac.za","Year_Established":1866,"Total_Student_Population":31000,"International_Student_Percentage":10,"Acceptance_Rate_Percentage":50,"Annual_Tuition_Fees_USD":4000,"QS_World_Ranking":289,"Key_Programs_Specializations":"Agriculture, Engineering, Sciences, Business","Research_Output_Level":"High"},
  {"Institution_Name":"American University in Cairo","Country":"Egypt","Region_State_Province":"Cairo Governorate","City":"Cairo","Institution_Type":"Private","Website_URL":"https://www.aucegypt.edu","Year_Established":1919,"Total_Student_Population":6500,"International_Student_Percentage":20,"Acceptance_Rate_Percentage":45,"Annual_Tuition_Fees_USD":20000,"QS_World_Ranking":420,"Key_Programs_Specializations":"Business, Engineering, Humanities, Sciences","Research_Output_Level":"Medium"},
  {"Institution_Name":"Cairo University","Country":"Egypt","Region_State_Province":"Giza Governorate","City":"Giza","Institution_Type":"Public","Website_URL":"https://cu.edu.eg","Year_Established":1908,"Total_Student_Population":200000,"International_Student_Percentage":5,"Acceptance_Rate_Percentage":70,"Annual_Tuition_Fees_USD":500,"QS_World_Ranking":371,"Key_Programs_Specializations":"Medicine, Engineering, Law, Sciences","Research_Output_Level":"Medium"},
  {"Institution_Name":"University of Lagos","Country":"Nigeria","Region_State_Province":"Lagos State","City":"Lagos","Institution_Type":"Public","Website_URL":"https://www.unilag.edu.ng","Year_Established":1962,"Total_Student_Population":57000,"International_Student_Percentage":3,"Acceptance_Rate_Percentage":40,"Annual_Tuition_Fees_USD":1000,"QS_World_Ranking":801,"Key_Programs_Specializations":"Engineering, Medicine, Law, Sciences","Research_Output_Level":"Medium"},
  {"Institution_Name":"University of Nairobi","Country":"Kenya","Region_State_Province":"Nairobi County","City":"Nairobi","Institution_Type":"Public","Website_URL":"https://www.uonbi.ac.ke","Year_Established":1956,"Total_Student_Population":84000,"International_Student_Percentage":5,"Acceptance_Rate_Percentage":50,"Annual_Tuition_Fees_USD":2000,"QS_World_Ranking":801,"Key_Programs_Specializations":"Medicine, Engineering, Sciences, Law","Research_Output_Level":"Medium"},
  {"Institution_Name":"University of Ghana","Country":"Ghana","Region_State_Province":"Greater Accra","City":"Accra","Institution_Type":"Public","Website_URL":"https://www.ug.edu.gh","Year_Established":1948,"Total_Student_Population":45000,"International_Student_Percentage":8,"Acceptance_Rate_Percentage":55,"Annual_Tuition_Fees_USD":1500,"QS_World_Ranking":801,"Key_Programs_Specializations":"Sciences, Medicine, Business, Law","Research_Output_Level":"Medium"},
  {"Institution_Name":"Makerere University","Country":"Uganda","Region_State_Province":"Central Region","City":"Kampala","Institution_Type":"Public","Website_URL":"https://www.mak.ac.ug","Year_Established":1922,"Total_Student_Population":40000,"International_Student_Percentage":5,"Acceptance_Rate_Percentage":45,"Annual_Tuition_Fees_USD":1500,"QS_World_Ranking":801,"Key_Programs_Specializations":"Medicine, Agriculture, Sciences, Education","Research_Output_Level":"Medium"}
]
